Metadata-Version: 2.1
Name: nor
Version: 0.1.0
Summary: A simple test for a machine learning framework
Author: Rtisty
Author-email: ops.em@outlook.com
Classifier: Programming Language :: Python :: 3
Classifier: License :: OSI Approved :: MIT License
Classifier: Operating System :: OS Independent
Requires-Dist: numpy>=1.22
